silverbullet/__init__.py
silverbullet/color.py
silverbullet/connection.py
silverbullet/robot.py
silverbullet/scene.py
silverbullet-0.3.0.dist-info/LICENSE
silverbullet-0.3.0.dist-info/WHEEL
silverbullet-0.3.0.dist-info/METADATA
silverbullet-0.3.0.dist-info/RECORD
